README.md
setup.py
cli/__init__.py
cli/constants.py
cli/main.py
cli/approximate_cost/__init__.py
cli/approximate_cost/cost.py
cli/cost/__init__.py
cli/cost/embeddings.py
cli/cost/input.py
cli/cost/output.py
cli/doc/doc.md
cli/evals/__init__.py
cli/evals/classification.py
cli/evals/code_generation.py
cli/evals/elovalue.py
cli/evals/equals.py
cli/evals/function_calling.py
cli/evals/includes.py
cli/evals/json_validation.py
cli/evals/semantic_similarity.py
cli/openai_calls/__init__.py
cli/openai_calls/openai_call.py
cli/prompt_generation/__init__.py
cli/prompt_generation/generation.py
cli/prompt_generation/iteration.py
cli/validation_yaml/__init__.py
cli/validation_yaml/validation.py
lenio_ai_prompt_engineer.egg-info/PKG-INFO
lenio_ai_prompt_engineer.egg-info/SOURCES.txt
lenio_ai_prompt_engineer.egg-info/dependency_links.txt
lenio_ai_prompt_engineer.egg-info/entry_points.txt
lenio_ai_prompt_engineer.egg-info/requires.txt
lenio_ai_prompt_engineer.egg-info/top_level.txt