Metadata-Version: 2.1
Name: lenio-ai-prompt-engineer
Version: 1.6.2
Summary: Prompt Engineer (lenio-ai-prompt-engineer) is a package for evaluating custom prompts using various evaluation methods. It allows you to provide your own prompts or generate them automatically and then obtain the results in a JSON file.
Requires-Python: >=3.8
